harmony/__init__.py
harmony/main.py
harmony_amc-0.0.5.dist-info/LICENSE
harmony_amc-0.0.5.dist-info/METADATA
harmony_amc-0.0.5.dist-info/WHEEL
harmony_amc-0.0.5.dist-info/top_level.txt
harmony_amc-0.0.5.dist-info/RECORD
